ai_sdk/__init__.py
ai_sdk/client.py
ai_sdk/exceptions.py
ai_sdk/auth/__init__.py
ai_sdk/auth/api_key.py
ai_sdk/core/__init__.py
ai_sdk/core/config.py
ai_sdk/core/error_handler.py
ai_sdk/core/http_client.py
ai_sdk/core/utils.py
ai_sdk/providers/__init__.py
ai_sdk/providers/base.py
ai_sdk/providers/litellm_provider.py
ai_sdk/providers/openai_provider.py
ai_sdk/providers/vllm_provider.py
ai_sdk/streaming/__init__.py
ai_sdk/streaming/event_stream.py
ai_sdk/streaming/simple_stream.py
nexgen_sdk-0.1.2.dist-info/licenses/LICENSE
nexgen_sdk-0.1.2.dist-info/METADATA
nexgen_sdk-0.1.2.dist-info/WHEEL
nexgen_sdk-0.1.2.dist-info/top_level.txt
nexgen_sdk-0.1.2.dist-info/RECORD
