Metadata-Version: 2.4
Name: nexgen-sdk
Version: 0.1.2
Summary: A custom Python SDK for interacting with AI models, compatible with OpenAI's API format
Author-email: Dhruv Karnwal <kdhruv.fsd@gmail.com>
License-Expression: MIT
Project-URL: Homepage, https://github.com/Dhruv1969Karnwal/ai-sdk-python
Project-URL: Documentation, https://ai-sdk.readthedocs.io
Project-URL: Repository, https://github.com/Dhruv1969Karnwal/ai-sdk-python.git
Project-URL: Issues, https://github.com/Dhruv1969Karnwal/ai-sdk-python/issues
Keywords: ai,openai,sdk,machine-learning,nlp,llm,chatbot
Classifier: Development Status :: 3 - Alpha
Classifier: Intended Audience :: Developers
Classifier: Programming Language :: Python :: 3
Classifier: Programming Language :: Python :: 3.7
Classifier: Programming Language :: Python :: 3.8
Classifier: Programming Language :: Python :: 3.9
Classifier: Programming Language :: Python :: 3.10
Classifier: Programming Language :: Python :: 3.11
Classifier: Programming Language :: Python :: 3.12
Classifier: Topic :: Software Development :: Libraries :: Python Modules
Classifier: Topic :: Scientific/Engineering :: Artificial Intelligence
License-File: LICENSE
Requires-Dist: httpx<1.0.0,>=0.23.0
Requires-Dist: typing_extensions>=3.7.4; python_version < "3.8"
Provides-Extra: dev
Requires-Dist: pytest>=7.0.0; extra == "dev"
Requires-Dist: pytest-asyncio>=0.20.0; extra == "dev"
Requires-Dist: black>=22.0.0; extra == "dev"
Requires-Dist: flake8>=5.0.0; extra == "dev"
Requires-Dist: mypy>=0.950; extra == "dev"
Requires-Dist: tox>=3.25.0; extra == "dev"
Provides-Extra: docs
Requires-Dist: sphinx>=5.0.0; extra == "docs"
Requires-Dist: sphinx-rtd-theme>=1.0.0; extra == "docs"
Dynamic: license-file
